Metadata-Version: 2.1
Name: getedu
Version: 1.0.0
Summary: An API for E-Learning Cloud Platforms
Home-page: http://getedu.xyz/
Author: Code Ja Poe
Author-email: codejapoe@gmail.com
License: getEdu
Keywords: api
Platform: UNKNOWN
Classifier: Development Status :: 5 - Production/Stable
Classifier: Intended Audience :: Education
Classifier: Operating System :: Microsoft :: Windows :: Windows 10
Classifier: License :: OSI Approved :: MIT License
Classifier: Programming Language :: Python :: 3
License-File: LICENCE.txt
